{
	"description": "Hierarchical Encounter.locationID list in Wildbook",
	"source": "provided by researchers",
	"locationID": [
		{
			"name": "Antarctica",
			"id": "Antarctica",
			"geospatialInfo": {},
			"locationID": [
				{
					"name": "Cape Washington",
					"id": "Cape Washington",
					"geospatialInfo": {},
					"locationID": []
				},
				{
					"name": "Inexpressible Island",
					"id": "Inexpressible Island",
					"geospatialInfo": {},
					"locationID": []
				},
				{
					"name": "Terra Nova Bay",
					"id": "Terra Nova Bay",
					"geospatialInfo": {},
					"locationID": []
				}
			]
		},
		{
			"name": "Arctic Sea",
			"id": "Arctic Sea",
			"geospatialInfo": {},
			"locationID": [
				{
					"name": "Beaufort Sea",
					"id": "Beaufort Sea",
					"geospatialInfo": {},
					"locationID": []
				},
				{
					"name": "Chukchi Sea",
					"id": "Chukchi Sea",
					"geospatialInfo": {},
					"locationID": []
				},
				{
					"name": "Greenland Sea",
					"id": "Greenland Sea",
					"geospatialInfo": {},
					"locationID": []
				},
				{
					"name": "Hudson Bay",
					"id": "Hudson Bay",
					"geospatialInfo": {},
					"locationID": []
				}
			]
		},
		{
			"name": "Baltic Sea",
			"id": "Baltic Sea",
			"geospatialInfo": {},
			"locationID": [
				{
					"name": "Archipelago Sea",
					"id": "Archipelago Sea",
					"geospatialInfo": {},
					"locationID": []
				}
			]
		},
		{
			"name": "English Channel",
			"id": "English Channel",
			"geospatialInfo": {},
			"locationID": [
				{
					"name": "England",
					"id": "England",
					"geospatialInfo": {},
					"locationID": [
						{
						"name": "Brixham",
						"id": "Brixham",
						"geospatialInfo": {},
						"locationID": []
					}
				]
				}
			]
		},
		{
			"name": "Lake Saimaa",
			"id": "Lake Saimaa",
			"locationID": [
				{
					"name": "Etel채-Saimaa",
					"id": "Etel채-Saimaa",
					"geospatialInfo": {},
					"locationID": []
				},
				{
					"name": "Haukivesi",
					"id": "Haukivesi",
					"geospatialInfo": {},
					"locationID": []
				},
				{
					"name": "Joutenvesi",
					"id": "Joutenvesi",
					"geospatialInfo": {},
					"locationID": []
				},
				{
					"name": "Katosselk채",
					"id": "Katosselk채",
					"geospatialInfo": {},
					"locationID": []
				},
				{
					"name": "Kolovesi",
					"id": "Kolovesi",
					"geospatialInfo": {},
					"locationID": []
				},
				{
					"name": "Luonteri-Lietvesi",
					"id": "Luonteri-Lietvesi",
					"geospatialInfo": {},
					"locationID": []
				},
				{
					"name": "Pihlajavesi",
					"id": "Pihlajavesi",
					"geospatialInfo": {},
					"locationID": []
				},
				{
					"name": "Pohjois-Saimaa",
					"id": "Pohjois-Saimaa",
					"geospatialInfo": {},
					"locationID": []
				},
				{
					"name": "Puruvesi",
					"id": "Puruvesi",
					"geospatialInfo": {},
					"locationID": []
				},
				{
					"name": "Pyyvesi-Enonvesi",
					"id": "Pyyvesi-Enonvesi",
					"geospatialInfo": {},
					"locationID": []
				}
			]
		},
		{
			"name": "Mediterranean Sea",
			"id": "Mediterranean Sea",
			"geospatialInfo": {},
			"locationID": [
				{
					"name": "Cyprus",
					"id": "Cyprus",
					"geospatialInfo": {},
					"locationID": []
				},
				{
					"name": "Greece",
					"id": "Greece",
					"geospatialInfo": {},
					"locationID": []
				},
				{
					"name": "Israel",
					"id": "Israel",
					"geospatialInfo": {},
					"locationID": [
						{
						"name": "Herzeliya",
						"id": "Herzeliya",
						"geospatialInfo": {},
						"locationID": []
					},
					{
						"name": "Rosh Hanikra",
						"id": "Rosh Hanikra",
						"geospatialInfo": {},
						"locationID": []
					}
				]
				},
				{
					"name": "Turkey",
					"id": "Turkey",
					"geospatialInfo": {},
					"locationID": []
				}
			]
		},
		{
			"name": "US Atlantic",
			"id": "US Atlantic",
			"geospatialInfo": {},
			"locationID": [
				{
					"name": "Delaware",
					"id": "Delaware",
					"geospatialInfo": {},
					"locationID": [
						{
						"name": "Delaware Bay",
						"id": "Delaware Bay",
						"geospatialInfo": {},
						"locationID": []
					}
				]
				},
				{
					"name": "New York",
					"id": "New York",
					"geospatialInfo": {},
					"locationID": [
						{
						"name": "Long Island",
						"id": "Long Island",
						"geospatialInfo": {},
						"locationID": [
							{
								"name": "Moriches Bay",
								"id": "Moriches Bay",
								"geospatialInfo": {},
								"locationID": []
							}
						]
					}
				]
				}
			]
		},
		{
			"name": "US Pacific",
			"id": "US Pacific",
			"geospatialInfo": {},
			"locationID": [
				{
					"name": "Washington",
					"id": "Washington",
					"geospatialInfo": {},
					"locationID": [
						{
						"name": "Anacortes",
						"id": "Anacortes",
						"geospatialInfo": {},
						"locationID": [
							{
								"name": "Salish Sea",
								"id": "Salish Sea",
								"geospatialInfo": {},
								"locationID": []
							}
						]
					}
				]
				}
			]
		}
		
	]
}
